Online/__init__.py
Online/online.py
OnlineCompile-0.5.2.dist-info/METADATA
OnlineCompile-0.5.2.dist-info/WHEEL
OnlineCompile-0.5.2.dist-info/top_level.txt
OnlineCompile-0.5.2.dist-info/RECORD
