Metadata-Version: 2.1
Name: OnlineCompile
Version: 0.5.2
Summary: A Python package for running python scripts from the internet
Home-page: UNKNOWN
Author: Will F
Author-email: forsbergw82@gmail.com
License: UNKNOWN
Platform: UNKNOWN
Classifier: Programming Language :: Python :: 3
